{
  "main": {
    "id": "469ee10b21171a35",
    "type": "split",
    "children": [
      {
        "id": "d660cf235a5e6757",
        "type": "tabs",
        "children": [
          {
            "id": "822dd3e84be5f291",
            "type": "leaf",
            "state": {
              "type": "excalidraw",
              "state": {
                "file": "artifacts/Excalidraw/dynamodb_lab.excalidraw.md"
              }
            }
          }
        ]
      }
    ],
    "direction": "vertical"
  },
  "left": {
    "id": "5e92b8b4b773468c",
    "type": "split",
    "children": [
      {
        "id": "ef15c09dcf7f44b4",
        "type": "tabs",
        "children": [
          {
            "id": "a46557e53235867d",
            "type": "leaf",
            "state": {
              "type": "file-explorer",
              "state": {
                "sortOrder": "alphabetical"
              }
            }
          },
          {
            "id": "62164508f5461f06",
            "type": "leaf",
            "state": {
              "type": "search",
              "state": {
                "query": "",
                "matchingCase": false,
                "explainSearch": false,
                "collapseAll": false,
                "extraContext": false,
                "sortOrder": "alphabetical"
              }
            }
          },
          {
            "id": "53036101d2a8952c",
            "type": "leaf",
            "state": {
              "type": "starred",
              "state": {}
            }
          }
        ]
      }
    ],
    "direction": "horizontal",
    "width": 409.5
  },
  "right": {
    "id": "600b784b70fa4fdd",
    "type": "split",
    "children": [
      {
        "id": "14f26d3c5249f6dd",
        "type": "tabs",
        "children": [
          {
            "id": "019069ff4b539460",
            "type": "leaf",
            "state": {
              "type": "backlink",
              "state": {
                "file": "artifacts/Excalidraw/dynamodb_lab.excalidraw.md",
                "collapseAll": false,
                "extraContext": false,
                "sortOrder": "alphabetical",
                "showSearch": false,
                "searchQuery": "",
                "backlinkCollapsed": false,
                "unlinkedCollapsed": true
              }
            }
          },
          {
            "id": "6d0be266bffc5bb8",
            "type": "leaf",
            "state": {
              "type": "outgoing-link",
              "state": {
                "file": "artifacts/Excalidraw/dynamodb_lab.excalidraw.md",
                "linksCollapsed": false,
                "unlinkedCollapsed": true
              }
            }
          },
          {
            "id": "8fbdacabca3cf14f",
            "type": "leaf",
            "state": {
              "type": "tag",
              "state": {
                "sortOrder": "frequency",
                "useHierarchy": true
              }
            }
          },
          {
            "id": "405df46590c318d3",
            "type": "leaf",
            "state": {
              "type": "outline",
              "state": {
                "file": "artifacts/Excalidraw/dynamodb_lab.excalidraw.md"
              }
            }
          },
          {
            "id": "7fa49f743f4d7fc3",
            "type": "leaf",
            "state": {
              "type": "gptModelSettings",
              "state": {}
            }
          }
        ],
        "currentTab": 4
      }
    ],
    "direction": "horizontal",
    "width": 822.5,
    "collapsed": true
  },
  "left-ribbon": {
    "hiddenItems": {
      "switcher:Open quick switcher": false,
      "graph:Open graph view": false,
      "canvas:Create new canvas": false,
      "daily-notes:Open today's daily note": false,
      "templates:Insert template": false,
      "command-palette:Open command palette": false,
      "obsidian-advanced-slides:Show Slide Preview": false,
      "obsidian-excalidraw-plugin:Create new drawing": false
    }
  },
  "active": "822dd3e84be5f291",
  "lastOpenFiles": [
    "dynamodb/lab/Dynamodb.md",
    "artifacts/Excalidraw/dynamodb_lab.excalidraw.md",
    "artifacts/Excalidraw/Dynamodb_query_scan.excalidraw.md",
    "dynamodb/dynamodb-part-1.md",
    "dynamodb/dynamodb-part-1.md~",
    "artifacts/Excalidraw/Dynamodb_table.excalidraw.md",
    "dynamodb/Dynamodb getting start (part 1).md",
    "artifacts/Excalidraw/dynamodb_scan_1.svg",
    "artifacts/Excalidraw/dynamodb_query_filter.excalidraw",
    "artifacts/Excalidraw/Dynamodb Query.excalidraw.md",
    "artifacts/Excalidraw/dynamodb_lab.excalidraw.svg",
    "dynamodb/lab/dev/terragrunt.hcl~",
    "artifacts/Excalidraw/dynamodb_query_filter.svg",
    "dynamodb/lab/dev/backend.tf",
    "dynamodb/lab/dev/provider.tf",
    "dynamodb/lab/dev/versions.tf",
    "dynamodb/lab/dev/terragrunt.hcl",
    "terragrunt.hcl~",
    "terragrunt.hcl",
    "tf_modules/aws_kinesis/main.tf~",
    "artifacts/Excalidraw/dynamodb_query_pk.svg",
    "artifacts/Excalidraw/Dynamodb_query_scan.excalidraw.svg",
    "artifacts/Excalidraw/Dynamodb Query.excalidraw.svg",
    "artifacts/Excalidraw/Dynamodb_table.excalidraw.svg",
    "artifacts/Excalidraw/Scripts/Downloaded/Uniform size.svg",
    "artifacts/Excalidraw/Scripts/Downloaded/Uniform size.md",
    "Excalidraw/dynamodb_lab.excalidraw.png",
    "Excalidraw/dynamodb_lab.excalidraw.svg",
    "().md"
  ]
}